{
  "indexes": [
    {
      "collectionGroup": "connections",
      "queryScope": "COLLECTION",
      "fields": [
        { "fieldPath": "ownerId", "order": "ASCENDING" },
        { "fieldPath": "updatedAt", "order": "DESCENDING" }
      ]
    },
    {
      "collectionGroup": "contacts",
      "queryScope": "COLLECTION",
      "fields": [
        { "fieldPath": "ownerId", "order": "ASCENDING" },
        { "fieldPath": "connectionId", "order": "ASCENDING" },
        { "fieldPath": "updatedAt", "order": "DESCENDING" }
      ]
    },
    {
      "collectionGroup": "contacts",
      "queryScope": "COLLECTION",
      "fields": [
        { "fieldPath": "ownerId", "order": "ASCENDING" },
        { "fieldPath": "connectionId", "order": "ASCENDING" },
        { "fieldPath": "normalizedName", "order": "ASCENDING" }
      ]
    },
    {
      "collectionGroup": "contacts",
      "queryScope": "COLLECTION",
      "fields": [
        { "fieldPath": "ownerId", "order": "ASCENDING" },
        { "fieldPath": "connectionId", "order": "ASCENDING" },
        { "fieldPath": "normalizedPhone", "order": "ASCENDING" }
      ]
    },
    {
      "collectionGroup": "messages",
      "queryScope": "COLLECTION",
      "fields": [
        { "fieldPath": "ownerId", "order": "ASCENDING" },
        { "fieldPath": "connectionId", "order": "ASCENDING" },
        { "fieldPath": "updatedAt", "order": "DESCENDING" }
      ]
    },
    {
      "collectionGroup": "messages",
      "queryScope": "COLLECTION",
      "fields": [
        { "fieldPath": "ownerId", "order": "ASCENDING" },
        { "fieldPath": "connectionId", "order": "ASCENDING" },
        { "fieldPath": "status", "order": "ASCENDING" },
        { "fieldPath": "updatedAt", "order": "DESCENDING" }
      ]
    },
    {
      "collectionGroup": "messages",
      "queryScope": "COLLECTION",
      "fields": [
        { "fieldPath": "ownerId", "order": "ASCENDING" },
        { "fieldPath": "connectionId", "order": "ASCENDING" },
        { "fieldPath": "normalizedContent", "order": "ASCENDING" }
      ]
    },
    {
      "collectionGroup": "messages",
      "queryScope": "COLLECTION",
      "fields": [
        { "fieldPath": "ownerId", "order": "ASCENDING" },
        { "fieldPath": "connectionId", "order": "ASCENDING" },
        { "fieldPath": "status", "order": "ASCENDING" },
        { "fieldPath": "normalizedContent", "order": "ASCENDING" }
      ]
    },
    {
      "collectionGroup": "messages",
      "queryScope": "COLLECTION",
      "fields": [
        { "fieldPath": "status", "order": "ASCENDING" },
        { "fieldPath": "scheduledAt", "order": "ASCENDING" }
      ]
    }
  ],
  "fieldOverrides": []
}
